adafruit_circuitpython_featherwing-1.15.8.dist-info/licenses/LICENSE
adafruit_featherwing/__init__.py
adafruit_featherwing/alphanum_featherwing.py
adafruit_featherwing/auto_writeable.py
adafruit_featherwing/dotstar_featherwing.py
adafruit_featherwing/gps_featherwing.py
adafruit_featherwing/ina219_featherwing.py
adafruit_featherwing/joy_featherwing.py
adafruit_featherwing/keyboard_featherwing.py
adafruit_featherwing/led_segments.py
adafruit_featherwing/matrix_featherwing.py
adafruit_featherwing/minitft_featherwing.py
adafruit_featherwing/neopixel_featherwing.py
adafruit_featherwing/pixelmatrix.py
adafruit_featherwing/rtc_featherwing.py
adafruit_featherwing/sevensegment_featherwing.py
adafruit_featherwing/tempmotion_featherwing.py
adafruit_featherwing/tft_featherwing.py
adafruit_featherwing/tft_featherwing_24.py
adafruit_featherwing/tft_featherwing_35.py
adafruit_circuitpython_featherwing-1.15.8.dist-info/METADATA
adafruit_circuitpython_featherwing-1.15.8.dist-info/WHEEL
adafruit_circuitpython_featherwing-1.15.8.dist-info/top_level.txt
adafruit_circuitpython_featherwing-1.15.8.dist-info/RECORD
