Metadata-Version: 2.4
Name: adafruit-circuitpython-featherwing
Version: 1.15.8
Summary: CircuitPython library that provides FeatherWing specific classes for those that require a significant amount of initialization.
Author-email: Adafruit Industries <circuitpython@adafruit.com>
License: MIT
Project-URL: Homepage, https://github.com/adafruit/Adafruit_CircuitPython_FeatherWing
Keywords: adafruit,ina219,featherwing,joy,joywing,i2c,hardware,micropython,circuitpython
Classifier: Intended Audience :: Developers
Classifier: Topic :: Software Development :: Libraries
Classifier: Topic :: Software Development :: Embedded Systems
Classifier: Topic :: System :: Hardware
Classifier: License :: OSI Approved :: MIT License
Classifier: Programming Language :: Python :: 3
License-File: LICENSE
Requires-Dist: Adafruit-Blinka
Requires-Dist: adafruit-circuitpython-adt7410
Requires-Dist: adafruit-circuitpython-busdevice
Requires-Dist: adafruit-circuitpython-stmpe610
Requires-Dist: adafruit-circuitpython-ht16k33
Requires-Dist: adafruit-circuitpython-dotstar
Requires-Dist: adafruit-circuitpython-neopixel
Requires-Dist: adafruit-circuitpython-ina219
Requires-Dist: adafruit-circuitpython-ds3231
Requires-Dist: adafruit-circuitpython-ili9341
Requires-Dist: adafruit-circuitpython-gps
Requires-Dist: adafruit-circuitpython-register
Requires-Dist: adafruit-circuitpython-hx8357
Requires-Dist: adafruit-circuitpython-st7735r
Requires-Dist: adafruit-circuitpython-adxl34x
Requires-Dist: adafruit-circuitpython-seesaw
Requires-Dist: adafruit-circuitpython-tsc2007
Requires-Dist: adafruit-circuitpython-focaltouch
Provides-Extra: optional
Dynamic: license-file
